[
    {
      "url": "/web-modules/nav-container.html",
      "contenedorId": "navbar-container"
    },
    {
      "url": "/web-modules/footer-container.html",
      "contenedorId": "footer-container"
    },
    {
        "url": "/web-modules/main-container.html",
        "contenedorId": "main-container"
    },
    {
      "url": "/web-modules/chapter-module.html",
      "contenedorId": "chapter-module"
    },
    {
      "url": "/web-modules/comment-section.html",
      "contenedorId": "comment-section"
    }
  ]