{
  "episodes": [
    {
      "title": "E1 - A ti, 2,000 años en el futuro. La caída de Shiganshina - Primera Parte",
      "source": "https://streamwish.to/e/r5ikyog88shf"
    },
    {
      "title": "E2 - Ese día. La caída de Shiganshina - Primera Parte",
      "source": "https://mega.nz/embed/7XpHkYSQ#4ByZbVBidWNubWGpTlJPA4IXcMUqS0XBmgEz2hCyZS4"
    },
    {
      "title": "E3 - Una tenue luz en la desesperación. La humanidad se levanta de nuevo - Primera Parte",
      "source": "https://streamwish.to/e/ea1hjs33j9n9"
    },
    {
      "title": "E4 - La noche de la ceremonia de graduación. La humanidad se levanta de nuevo - Segunda Parte",
      "source": "https://streamwish.to/e/xdgy0afyrf95"
    },
    {
      "title": "E5 - Primera batalla. La batalla de Trost - Primera Parte",
      "source": "https://streamwish.to/e/73m9vh4vruo9"
    },
    {
      "title": "E6 - El mundo a los ojos de la chica. La batalla de Trost - Segunda Parte",
      "source": "https://streamwish.to/e/73m9vh4vruo9"
    },
    {
      "title": "E7 - Una pequeña hoja. La batalla de Trost (3)",
      "source": "https://streamwish.to/e/73m9vh4vruo9"
    },
    {
      "title": "E8 - Oigo sus latidos. La batalla de Trost (4)",
      "source": "https://streamwish.to/e/73m9vh4vruo9"
    },
    {
      "title": "E9 - El paradero del brazo izquierdo. La batalla de Trost (5)",
      "source": "https://streamwish.to/e/73m9vh4vruo9"
    },
    {
      "title": "E10 - Respuesta. La batalla de Trost (6)",
      "source": "https://streamwish.to/e/73m9vh4vruo9"
    },
    {
      "title": "E11 - Símbolo. La batalla de Trost (7)",
      "source": "https://streamwish.to/e/73m9vh4vruo9"
    },
    {
      "title": "E12 - Herida. La batalla de Trost (8)",
      "source": "https://streamwish.to/e/6eaz0tqakqnm"
    }
  ]
}